belinear/__init__.py
belinear/tests/__init__.py
belinear/tests/test_data.pickle
belinear/tests/tests.py
belinear-1.1.dist-info/LICENSE
belinear-1.1.dist-info/METADATA
belinear-1.1.dist-info/WHEEL
belinear-1.1.dist-info/top_level.txt
belinear-1.1.dist-info/RECORD
