Metadata-Version: 2.1
Name: belinear
Version: 1.1
Summary: Performant numerical solutions of the paraxial ray equation
Home-page: UNKNOWN
Author: Christopher M. Pierce
Author-email: contact@chris-pierce.com
License: GNU Lesser General Public License v3 (LGPLv3)
Platform: UNKNOWN
Classifier: Programming Language :: Python :: 3
Classifier: License :: OSI Approved :: GNU Lesser General Public License v3 (LGPLv3)
Classifier: Development Status :: 4 - Beta
Classifier: Operating System :: OS Independent
Requires-Python: >=3.5
Requires-Dist: numpy
Requires-Dist: matprod
Requires-Dist: scipy
